{
  "demographics": {
    "pangyo": {
      "population": 34879,
      "workers": 80344,
      "ratio": 2.304,
      "lum": 0.675
    },
    "cheongna": {
      "population": 78157,
      "workers": 61924,
      "ratio": 0.792,
      "lum": 0.603
    }
  },
  "industry_ratio": {
    "pangyo": {
      "정보통신업": 55,
      "전문과학기술업": 25,
      "제조업": 12,
      "기타": 8
    },
    "cheongna": {
      "금융보험업": 40,
      "운수창고업": 25,
      "제조업": 20,
      "기타": 15
    }
  },
  "building_uses": {
    "pangyo": {
      "업무시설": 2348026,
      "교육연구시설": 849753,
      "공동주택": 782514,
      "단독주택": 40278,
      "근린생활시설": 65345,
      "기타": 296058
    },
    "cheongna": {
      "업무시설": 641166,
      "교육연구시설": 71245,
      "공동주택": 1222294,
      "단독주택": 135385,
      "근린생활시설": 236082,
      "기타": 299413
    }
  },
  "land_use_zones": {
    "pangyo": {
      "주거지역": 10799,
      "상업·업무지역": 1576,
      "공업지역": 0,
      "녹지지역": 20896,
      "개발제한구역": 519,
      "기타/지구단위": 236780
    },
    "cheongna": {
      "주거지역": 12833,
      "상업·업무지역": 913,
      "공업지역": 7990,
      "녹지지역": 15643,
      "개발제한구역": 3288,
      "기타/지구단위": 130093
    }
  }
}